django_modelapiview/APIView.py
django_modelapiview/JSONMixin.py
django_modelapiview/ModelAPIView.py
django_modelapiview/Token.py
django_modelapiview/__init__.py
django_modelapiview/apps.py
django_modelapiview/decorators.py
django_modelapiview/responses.py
django_modelapiview/views.py
django_modelapiview/locale/fr/LC_MESSAGES/django.mo
django_modelapiview/locale/fr/LC_MESSAGES/django.po
django_modelapiview-1.4.15.dist-info/LICENSE
django_modelapiview-1.4.15.dist-info/METADATA
django_modelapiview-1.4.15.dist-info/WHEEL
django_modelapiview-1.4.15.dist-info/top_level.txt
django_modelapiview-1.4.15.dist-info/RECORD
