Metadata-Version: 2.1
Name: django-modelapiview
Version: 1.4.15
Summary: Two view classes to handle API endpoints
Home-page: https://github.com/TiphaineLAURENT/Django_APIView
Author: Tiphaine LAURENT
Author-email: tip.lau@hotmail.fr
License: BSD
Platform: any
Classifier: Environment :: Web Environment
Classifier: Intended Audience :: Developers
Classifier: License :: OSI Approved :: BSD License
Classifier: Operating System :: OS Independent
Classifier: Programming Language :: Python
Classifier: Topic :: Internet :: WWW/HTTP :: Dynamic Content
Classifier: Topic :: Software Development :: Libraries :: Python Modules
Requires-Python: >=3.9
Requires-Dist: Django (>=3.1)
Requires-Dist: django-routeview (>=1.1.0)
